Metadata-Version: 1.1
Name: cache-magic
Version: 1.0.0
Summary: Versatile cache line magic for jupyter notebooks, based on the awesome ipython-cache: https://pypi.org/project/ipython-cache/
Home-page: https://github.com/pyython/cache-magic
Author: Chris Piatt
Author-email: chris@pyython.com
License: BSD-3-Clause
Platform: UNKNOWN
Classifier: Development Status :: 7 - Inactive
Classifier: Intended Audience :: Developers
Classifier: Topic :: Software Development :: Libraries :: Python Modules
Classifier: Framework :: Jupyter
Classifier: Intended Audience :: Science/Research
Classifier: License :: Other/Proprietary License
Classifier: Programming Language :: Python :: 3.6
Classifier: Programming Language :: Python :: 3.7
Classifier: Topic :: Scientific/Engineering :: Information Analysis
